<?xml version="1.0" encoding="UTF-8" ?>
<Persons xmlns:xsi = "http://www.w3.org/2001/XMLSchema-instance"
    xsi:schemaLocation ="http://by.it.shishov/Persons Person.xsd"
    xmlns="http://by.it.shishov/Persons">
    <Person>
        <Email>asde@sfdfd.it</Email>
        <Nickname>asdd123</Nickname>
        <Password>qwerty</Password>
        <Ads>
            <Ad>
                <Descriprion>Отличный вариант</Descriprion>
                <Adress>Минск Ленина 29 кв. 5</Adress>
                <Floor>3</Floor>
                <Floors>5</Floors>
                <Square>49.0</Square>
                <Price>99999</Price>
            </Ad>
        </Ads>
    </Person>
</Persons>